rpa/rpa.v
module full_adder(
    input a,
    input b,
    input cin,
    output sum,
    output cout 
);

    wire c1, c2, c3;

    xor(c1, a, b);
    xor(sum, c1, cin);

    and(c2, a, b);
    and(c3, cin, c1);
    or(carry, c2, c3);

endmodule

module rpa(
    input  [7:0] a,
    input  [7:0] b,
    input        cin,
    output [7:0]sum,
    output       carry
);

    wire [7:0] c;
    

    

    full_adder ad0(a[0],~b[0]+1, cin ,  sum[0], c[0]);
    full_adder ad1(a[1], ~b[1]+1, c[0], sum[1], c[1]);
    full_adder ad2(a[2], ~b[2]+1, c[1],sum[2], c[2]);
    full_adder ad3(a[3], ~b[3]+1, c[2], sum[3], c[3]);
    full_adder ad4(a[4], ~b[4]+1, c[3], sum[4], c[4]);
    full_adder ad5(a[5], ~b[5]+1, c[4], sum[5], c[5]);
    full_adder ad6(a[6], ~b[6]+1, c[5],sum[6], c[6]);
    full_adder ad7(a[7], ~b[7]+1, c[6], sum[7], carry);


endmodule

rpa/full_adder_tb.v
module full_adder_tb;

    reg a;
    reg b;
    reg cin;

    wire sum;
    wire carry;

    full_adder uut (
        .a(a),
        .b(b),
        .cin(cin),
        .sum(sum),
        .carry(carry)
    );

    initial begin
        $dumpfile("full_adder.vcd");
        $dumpvars(0, full_adder_tb);

        a = 0; b = 0; cin = 0;
        #10;

        a = 0; b = 0; cin = 1;
        #10;

        a = 0; b = 1; cin = 0;
        #10;

        a = 0; b = 1; cin = 1;
        #10;

        a = 1; b = 0; cin = 0;
        #10;

        a = 1; b = 0; cin = 1;
        #10;

        a = 1; b = 1; cin = 0;
        #10;

        a = 1; b = 1; cin = 1;
        #10;

        $finish;
    end

endmodule

rpa/full_adder.vcd
$date
	Thu Aug 27 13:37:14 2026
$end
$version
	Icarus Verilog
$end
$timescale
	1s
$end
$scope module full_adder_tb $end
$var wire 1 ! carry $end
$var wire 1 " sum $end
$var reg 1 # a $end
$var reg 1 $ b $end
$var reg 1 % cin $end
$scope module uut $end
$var wire 1 & a $end
$var wire 1 ' b $end
$var wire 1 ( c1 $end
$var wire 1 ) c2 $end
$var wire 1 * c3 $end
$var wire 1 ! carry $end
$var wire 1 + cin $end
$var wire 1 " sum $end
$upscope $end
$upscope $end
$enddefinitions $end
#0
$dumpvars
0+
0*
0)
0(
0'
0&
0%
0$
0#
0"
0!
$end
#10
1"
1%
1+
#20
1(
0%
0+
1$
1'
#30
1!
0"
1*
1%
1+
#40
0!
1"
0*
0%
0+
0$
0'
1#
1&
#50
1!
0"
1*
1%
1+
#60
0*
0(
1)
0%
0+
1$
1'
#70
1"
1%
1+
